forcelayout/__init__.py
forcelayout/distance.py
forcelayout/draw.py
forcelayout/forcelayout.py
forcelayout/metrics.py
forcelayout/utils.py
forcelayout/algorithms/__init__.py
forcelayout/algorithms/base_spring_layout.py
forcelayout/algorithms/hybrid.py
forcelayout/algorithms/neighbour_sampling.py
forcelayout/algorithms/node.py
forcelayout/algorithms/pivot.py
forcelayout/algorithms/spring_force.py
forcelayout-1.0.6.dist-info/LICENSE
forcelayout-1.0.6.dist-info/METADATA
forcelayout-1.0.6.dist-info/WHEEL
forcelayout-1.0.6.dist-info/top_level.txt
forcelayout-1.0.6.dist-info/RECORD
