Metadata-Version: 2.1
Name: forcelayout
Version: 1.0.6
Summary: Force-directed layout algorithms for Python
Home-page: UNKNOWN
Author: Iain Cattermole
Author-email: iain_c@live.co.uk
License: MIT
Platform: UNKNOWN
Requires-Dist: numpy
Requires-Dist: matplotlib
